LICENSE
MANIFEST.in
README.md
setup.py
NlpToolkit_SentiNet_Cy.egg-info/PKG-INFO
NlpToolkit_SentiNet_Cy.egg-info/SOURCES.txt
NlpToolkit_SentiNet_Cy.egg-info/dependency_links.txt
NlpToolkit_SentiNet_Cy.egg-info/top_level.txt
SentiNet/PolarityType.py
SentiNet/SentiLiteral.c
SentiNet/SentiLiteral.pxd
SentiNet/SentiLiteral.pyx
SentiNet/SentiLiteralNet.c
SentiNet/SentiLiteralNet.pxd
SentiNet/SentiLiteralNet.pyx
SentiNet/SentiNet.c
SentiNet/SentiNet.pxd
SentiNet/SentiNet.pyx
SentiNet/SentiSynSet.c
SentiNet/SentiSynSet.pxd
SentiNet/SentiSynSet.pyx
SentiNet/__init__.py
SentiNet/data/__init__.py
SentiNet/data/turkish_sentiliteralnet.xml
SentiNet/data/turkish_sentinet.xml
nlptoolkit_sentinet_cy.egg-info/PKG-INFO
nlptoolkit_sentinet_cy.egg-info/SOURCES.txt
nlptoolkit_sentinet_cy.egg-info/dependency_links.txt
nlptoolkit_sentinet_cy.egg-info/top_level.txt