Metadata-Version: 2.4
Name: nlptoolkit-sentinet-cy
Version: 1.0.9
Summary: Turkish SentiNet
Home-page: https://github.com/StarlangSoftware/TurkishSentiNet-Cy
Author: olcaytaner
Author-email: olcay.yildiz@ozyegin.edu.tr
License-File: LICENSE
Dynamic: author
Dynamic: author-email
Dynamic: description
Dynamic: description-content-type
Dynamic: home-page
Dynamic: license-file
Dynamic: summary
